digicubes_rest/__init__.py
digicubes_rest/exceptions.py
digicubes_rest/structures.py
digicubes_rest/version.json
digicubes_rest/bin/__init__.py
digicubes_rest/bin/command.py
digicubes_rest/server/__init__.py
digicubes_rest/server/commandline.py
digicubes_rest/server/middleware.py
digicubes_rest/server/cfg/__init__.py
digicubes_rest/server/cfg/apiserver_default.py
digicubes_rest/server/cfg/apiserver_test.py
digicubes_rest/server/cfg/default_configuration.yaml
digicubes_rest/server/cfg/templates/__init__.py
digicubes_rest/server/cfg/templates/configuration.yaml
digicubes_rest/server/cfg/templates/logging.yaml
digicubes_rest/server/graphql/__init__.py
digicubes_rest/server/graphql/schema/__init__.py
digicubes_rest/server/graphql/schema/queries.py
digicubes_rest/server/graphql/schema/types.py
digicubes_rest/server/ressource/__init__.py
digicubes_rest/server/ressource/course.py
digicubes_rest/server/ressource/info.py
digicubes_rest/server/ressource/login.py
digicubes_rest/server/ressource/me.py
digicubes_rest/server/ressource/me_rights.py
digicubes_rest/server/ressource/me_roles.py
digicubes_rest/server/ressource/me_schools.py
digicubes_rest/server/ressource/password.py
digicubes_rest/server/ressource/renew_token.py
digicubes_rest/server/ressource/right.py
digicubes_rest/server/ressource/right_role.py
digicubes_rest/server/ressource/right_roles.py
digicubes_rest/server/ressource/rights.py
digicubes_rest/server/ressource/role.py
digicubes_rest/server/ressource/role_right.py
digicubes_rest/server/ressource/role_rights.py
digicubes_rest/server/ressource/roles.py
digicubes_rest/server/ressource/school.py
digicubes_rest/server/ressource/school_courses.py
digicubes_rest/server/ressource/school_students.py
digicubes_rest/server/ressource/schools.py
digicubes_rest/server/ressource/units.py
digicubes_rest/server/ressource/user.py
digicubes_rest/server/ressource/user_rights.py
digicubes_rest/server/ressource/user_role.py
digicubes_rest/server/ressource/user_roles.py
digicubes_server-0.1.27.dist-info/METADATA
digicubes_server-0.1.27.dist-info/WHEEL
digicubes_server-0.1.27.dist-info/entry_points.txt
digicubes_server-0.1.27.dist-info/top_level.txt
digicubes_server-0.1.27.dist-info/RECORD
