Metadata-Version: 2.1
Name: digicubes-server
Version: 0.1.27
Summary: The digicubes api server
Home-page: UNKNOWN
Author: Klaas Nebuhr, Marion Nebuhr
Author-email: klaas.nebuhr@gmail.com
License: Apache License Version 2.0
Keywords: rest digicubes api learning platform
Platform: UNKNOWN
Classifier: License :: OSI Approved :: Apache Software License
Classifier: Development Status :: 3 - Alpha
Classifier: Intended Audience :: Developers
Classifier: Programming Language :: Python :: 3
Classifier: Programming Language :: Python :: 3.6
Classifier: Programming Language :: Python :: 3.7
Classifier: Framework :: AsyncIO
Classifier: Topic :: Software Development :: Libraries :: Python Modules
Classifier: Operating System :: OS Independent
Requires-Dist: aiofiles (==0.5.0)
Requires-Dist: aiosqlite (==0.15.0)
Requires-Dist: aniso8601 (==7.0.0)
Requires-Dist: apispec (==3.3.1)
Requires-Dist: apistar (==0.7.2)
Requires-Dist: attrs (==19.3.0)
Requires-Dist: cattrs (==1.0.0)
Requires-Dist: certifi (==2020.6.20)
Requires-Dist: chardet (==3.0.4)
Requires-Dist: click (==7.1.2)
Requires-Dist: css-html-js-minify (==2.5.5)
Requires-Dist: docopt (==0.6.2)
Requires-Dist: graphene (==2.1.8)
Requires-Dist: graphql-core (==2.3.2)
Requires-Dist: graphql-relay (==2.0.1)
Requires-Dist: graphql-server-core (==2.0.0)
Requires-Dist: h11 (==0.9.0)
Requires-Dist: httptools (==0.0.13)
Requires-Dist: idna (==2.10)
Requires-Dist: iso8601 (==0.1.12)
Requires-Dist: itsdangerous (==1.1.0)
Requires-Dist: jinja2 (==2.11.2)
Requires-Dist: libgravatar (==0.2.4)
Requires-Dist: markupsafe (==1.1.1)
Requires-Dist: marshmallow (==3.7.1)
Requires-Dist: promise (==2.3)
Requires-Dist: pyjwt (==1.7.1)
Requires-Dist: pypika (==0.38.0)
Requires-Dist: python-dotenv (==0.14.0)
Requires-Dist: python-multipart (==0.0.5)
Requires-Dist: pyyaml (==5.3.1)
Requires-Dist: requests-toolbelt (==0.9.1)
Requires-Dist: requests (==2.24.0)
Requires-Dist: responder (==2.0.5)
Requires-Dist: rfc3986 (==1.4.0)
Requires-Dist: rx (==1.6.1)
Requires-Dist: six (==1.15.0)
Requires-Dist: starlette (==0.12.13)
Requires-Dist: tortoise-orm (==0.16.14)
Requires-Dist: typesystem (==0.2.4)
Requires-Dist: typing-extensions (==3.7.4.2)
Requires-Dist: urllib3 (==1.25.10)
Requires-Dist: uvicorn (==0.10.9)
Requires-Dist: uvloop (==0.14.0)
Requires-Dist: websockets (==8.1)
Requires-Dist: werkzeug (==1.0.1)
Requires-Dist: whitenoise (==5.2.0)
